conllviewer/__init__.py
conllviewer/viewer.py
conllviewer/fonts/BabelSans.ttf
conllviewer/fonts/Exo-Medium.otf
conllviewer/fonts/PRIMERB.ttf
ConllViewer-1.0.0.dist-info/LICENSE
ConllViewer-1.0.0.dist-info/METADATA
ConllViewer-1.0.0.dist-info/WHEEL
ConllViewer-1.0.0.dist-info/top_level.txt
ConllViewer-1.0.0.dist-info/RECORD
