Metadata-Version: 2.1
Name: ConllViewer
Version: 1.0.0
Summary: Visually representing a CONLL 2009 files
Home-page: https://github.com/taoprajjwal/conll-viewer/
Author: Prajjwal Bhattarai
Author-email: taoprajjwal@gmail.com
License: MIT
Platform: UNKNOWN
Classifier: License :: OSI Approved :: MIT License
Classifier: Programming Language :: Python :: 3
Classifier: Programming Language :: Python :: 3.7
Requires-Dist: Pillow
